LICENSE
README.md
setup.py
tap_crossbeam/__init__.py
tap_crossbeam/client.py
tap_crossbeam/discover.py
tap_crossbeam/endpoints.py
tap_crossbeam/sync.py
tap_crossbeam.egg-info/PKG-INFO
tap_crossbeam.egg-info/SOURCES.txt
tap_crossbeam.egg-info/dependency_links.txt
tap_crossbeam.egg-info/entry_points.txt
tap_crossbeam.egg-info/requires.txt
tap_crossbeam.egg-info/top_level.txt
tap_crossbeam/schemas/partner_populations.json
tap_crossbeam/schemas/partners.json
tap_crossbeam/schemas/populations.json
tap_crossbeam/schemas/thread_timelines.json
tap_crossbeam/schemas/threads.json