Metadata-Version: 2.1
Name: tap-crossbeam
Version: 0.4.1
Summary: Singer.io tap for extracting data from the Crossbeam API
Home-page: UNKNOWN
License: UNKNOWN
Platform: UNKNOWN
Classifier: Programming Language :: Python :: 3 :: Only
Provides-Extra: test
Provides-Extra: dev
License-File: LICENSE
